openrobots.libs/libcppad_lib.so.712.8
openrobots.libs/libpycppad.so
pycppad/__init__.py
pycppad/pycppad_pywrap.cpython-37m-x86_64-linux-gnu.so
pycppad-1.2.0.dist-info/METADATA
pycppad-1.2.0.dist-info/WHEEL
pycppad-1.2.0.dist-info/top_level.txt
pycppad-1.2.0.dist-info/RECORD
