Metadata-Version: 2.1
Name: pycppad
Version: 1.2.0
Summary: CppAD bindings to python
Home-page: https://github.com/Simple-Robotics/pycppad
Classifier: Programming Language :: Python :: 2
Classifier: Programming Language :: Python :: 3
Classifier: License :: OSI Approved :: BSD License
Classifier: Operating System :: POSIX :: Linux
Requires-Python: >= 2.7
Requires-Dist: numpy
Requires-Dist: eigenpy
